orderly_web/__about__.py
orderly_web/__init__.py
orderly_web/admin.py
orderly_web/cli.py
orderly_web/config.py
orderly_web/constellation.py
orderly_web/docker_helpers.py
orderly_web/errors.py
orderly_web/pull.py
orderly_web/start.py
orderly_web/status.py
orderly_web/stop.py
orderly_web/static/wait_for_redis
orderly_web-1.4.6.dist-info/METADATA
orderly_web-1.4.6.dist-info/WHEEL
orderly_web-1.4.6.dist-info/entry_points.txt
orderly_web-1.4.6.dist-info/licenses/LICENSE
orderly_web-1.4.6.dist-info/RECORD
