Metadata-Version: 2.4
Name: orderly-web
Version: 1.4.6
Summary: Deploy scripts for OrderlyWeb
Project-URL: Homepage, https://github.com/vimc/orderly-web-deploy
Author-email: Rich FitzJohn <r.fitzjohn@imperial.ac.uk>
License-Expression: MIT
License-File: LICENSE
Classifier: License :: OSI Approved :: MIT License
Classifier: Operating System :: OS Independent
Classifier: Programming Language :: Python :: 3
Requires-Dist: constellation~=1.4.0
Requires-Dist: docker
Requires-Dist: docopt
Requires-Dist: hvac
Requires-Dist: pillow
Requires-Dist: pytest
Requires-Dist: pyyaml
Requires-Dist: vault-dev
